democrite.py
democrite-4.3.0.dist-info/METADATA
democrite-4.3.0.dist-info/WHEEL
democrite-4.3.0.dist-info/top_level.txt
democrite-4.3.0.dist-info/RECORD
