Metadata-Version: 2.1
Name: democrite
Version: 4.3.0
Summary: Library use to construct VGrain to democrite servers
Author-email: Nexai <info@nexai.net>
Project-URL: Homepage, https://github.com/Nexai-net/democrite
Project-URL: Issues, https://github.com/Nexai-net/democrite/issues
Classifier: Development Status :: 4 - Beta
Classifier: Programming Language :: Python :: 3
Classifier: License :: OSI Approved :: MIT License
Classifier: Operating System :: OS Independent
Requires-Python: >=3.8
